LICENSE
better_highlighting/__init__.py
better_highlighting/better_highlitghting.py
better_highlighting/components/__init__.py
better_highlighting/components/colors.py
better_highlighting/components/creator.py
better_highlighting/components/fonts.py
better_highlighting/components/highlighters.py
better_highlighting/components/lexers_and_styles/__init__.py
better_highlighting/components/lexers_and_styles/json_lexer.py
better_highlighting/components/lexers_and_styles/style_builders.py
better_highlighting/data_format.py
better_highlighting-2.0.0.dist-info/LICENSE
better_highlighting-2.0.0.dist-info/WHEEL
better_highlighting-2.0.0.dist-info/METADATA
better_highlighting-2.0.0.dist-info/RECORD
