Metadata-Version: 2.1
Name: better-highlighting
Version: 2.0.0
Summary: Small tool for text and syntax highlight.
Home-page: https://github.com/vskarinov/better_highlighting
License: MIT
Author: vskarinov
Author-email: skarinov27@gmail.com
Requires-Python: >=3.9,<4.0
Classifier: License :: OSI Approved :: MIT License
Classifier: Programming Language :: Python :: 3
Classifier: Programming Language :: Python :: 3.10
Classifier: Programming Language :: Python :: 3.9
Requires-Dist: Pygments (>=2.11.2,<3.0.0)
Requires-Dist: pandas (>=1.4.1,<2.0.0)
Requires-Dist: pytest (>=7.2.0,<8.0.0)
Requires-Dist: tabulate (>=0.8.9,<0.9.0)
Project-URL: Repository, https://github.com/vskarinov/better_highlighting
